restrictedpickle/__init__.py
restrictedpickle/classic.py
restrictedpickle/sPickle.py
restrictedpickle-0.3.0.dist-info/LICENSE
restrictedpickle-0.3.0.dist-info/METADATA
restrictedpickle-0.3.0.dist-info/WHEEL
restrictedpickle-0.3.0.dist-info/top_level.txt
restrictedpickle-0.3.0.dist-info/RECORD
