Metadata-Version: 2.1
Name: restrictedpickle
Version: 0.3.0
Summary: Python with braces
Home-page: https://github.com/ershov/restrictedpickle
Author: Yury Ershov
License: GPL3
License-File: LICENSE
